README.rst
setup.py
libmunin.egg-info/PKG-INFO
libmunin.egg-info/SOURCES.txt
libmunin.egg-info/dependency_links.txt
libmunin.egg-info/requires.txt
libmunin.egg-info/top_level.txt
munin/__init__.py
munin/__main__.py
munin/database.py
munin/dbus_client.py
munin/dbus_service.py
munin/easy.py
munin/graph.py
munin/helper.py
munin/history.py
munin/logutil.py
munin/plot.py
munin/rake.py
munin/session.py
munin/song.py
munin/testing.py
munin/distance/__init__.py
munin/distance/bpm.py
munin/distance/date.py
munin/distance/genre.py
munin/distance/keywords.py
munin/distance/levenshtein.py
munin/distance/moodbar.py
munin/distance/rating.py
munin/distance/wordlist.py
munin/provider/__init__.py
munin/provider/bpm.py
munin/provider/composite.py
munin/provider/date.py
munin/provider/generate_genre_list.py
munin/provider/genre.list
munin/provider/genre.py
munin/provider/keywords.py
munin/provider/moodbar.py
munin/provider/normalize.py
munin/provider/stem.py
munin/provider/wordlist.py
munin/scripts/__init__.py
munin/scripts/moodbar_visualizer.py
munin/scripts/moodbar_walk.py
munin/stopwords/README
munin/stopwords/__init__.py
munin/stopwords/__pycache__
munin/stopwords/data
munin/stopwords/data/ar
munin/stopwords/data/cs
munin/stopwords/data/da
munin/stopwords/data/de
munin/stopwords/data/en
munin/stopwords/data/es
munin/stopwords/data/fi
munin/stopwords/data/fr
munin/stopwords/data/hu
munin/stopwords/data/it
munin/stopwords/data/la
munin/stopwords/data/nl
munin/stopwords/data/pt
munin/stopwords/data/ru
munin/stopwords/data/se
munin/stopwords/data/tr