Metadata-Version: 1.0
Name: libmunin
Version: 0.05
Summary: Fancy library for music recommendations, based on datamining algorithms
Home-page: http://libmunin.rtfd.org/
Author: Christopher Pahl
Author-email: sahib@online.de
License: GPLv3
Platform: UNKNOWN
